optimove/__init__.py
optimove/actions.py
optimove/client.py
optimove/constants.py
optimove/customers.py
optimove/general.py
optimove/groups.py
optimove/integrations.py
optimove/model.py
optimove/segments.py
optimove-2.0.0.dist-info/DESCRIPTION.rst
optimove-2.0.0.dist-info/METADATA
optimove-2.0.0.dist-info/RECORD
optimove-2.0.0.dist-info/WHEEL
optimove-2.0.0.dist-info/metadata.json
optimove-2.0.0.dist-info/top_level.txt
tests/__init__.py
tests/constants.py
tests/helpers.py
tests/test_actions.py
tests/test_customers.py
tests/test_general.py
tests/test_groups.py
tests/test_integrations.py
tests/test_model.py
tests/test_segments.py
