Metadata-Version: 2.0
Name: optimove
Version: 2.0.0
Summary: This library allows you to quickly and easily use the Optimove Web API v3 via Python
Home-page: https://github.com/nicolasramy/optimove
Author: Nicolas RAMY
Author-email: nicolas.ramy@darkelda.com
License: MIT
Platform: UNKNOWN
Classifier: Development Status :: 4 - Beta
Classifier: License :: OSI Approved :: MIT License
Classifier: Operating System :: OS Independent
Classifier: Programming Language :: Python :: 2.7
Classifier: Programming Language :: Python :: 3.5
Classifier: Programming Language :: Python :: 3.6
Requires-Dist: requests
Requires-Dist: six
Requires-Dist: urllib3[secure]
